aliyunsdkamqp_open/__init__.py
aliyunsdkamqp_open/endpoint.py
aliyunsdkamqp_open/request/__init__.py
aliyunsdkamqp_open/request/v20191212/CreateAccountRequest.py
aliyunsdkamqp_open/request/v20191212/CreateBindingRequest.py
aliyunsdkamqp_open/request/v20191212/CreateExchangeRequest.py
aliyunsdkamqp_open/request/v20191212/CreateInstanceRequest.py
aliyunsdkamqp_open/request/v20191212/CreateQueueRequest.py
aliyunsdkamqp_open/request/v20191212/CreateVirtualHostRequest.py
aliyunsdkamqp_open/request/v20191212/DeleteAccountRequest.py
aliyunsdkamqp_open/request/v20191212/DeleteBindingRequest.py
aliyunsdkamqp_open/request/v20191212/DeleteExchangeRequest.py
aliyunsdkamqp_open/request/v20191212/DeleteQueueRequest.py
aliyunsdkamqp_open/request/v20191212/DeleteVirtualHostRequest.py
aliyunsdkamqp_open/request/v20191212/GetMetadataAmountRequest.py
aliyunsdkamqp_open/request/v20191212/ListAccountsRequest.py
aliyunsdkamqp_open/request/v20191212/ListBindingsRequest.py
aliyunsdkamqp_open/request/v20191212/ListDownStreamBindingsRequest.py
aliyunsdkamqp_open/request/v20191212/ListExchangeUpStreamBindingsRequest.py
aliyunsdkamqp_open/request/v20191212/ListExchangesRequest.py
aliyunsdkamqp_open/request/v20191212/ListInstancesRequest.py
aliyunsdkamqp_open/request/v20191212/ListQueueConsumersRequest.py
aliyunsdkamqp_open/request/v20191212/ListQueueUpStreamBindingsRequest.py
aliyunsdkamqp_open/request/v20191212/ListQueuesRequest.py
aliyunsdkamqp_open/request/v20191212/ListVirtualHostsRequest.py
aliyunsdkamqp_open/request/v20191212/UpdateInstanceNameRequest.py
aliyunsdkamqp_open/request/v20191212/UpdateInstanceRequest.py
aliyunsdkamqp_open/request/v20191212/__init__.py
aliyun_python_sdk_amqp_open-1.1.4.dist-info/LICENSE
aliyun_python_sdk_amqp_open-1.1.4.dist-info/METADATA
aliyun_python_sdk_amqp_open-1.1.4.dist-info/WHEEL
aliyun_python_sdk_amqp_open-1.1.4.dist-info/top_level.txt
aliyun_python_sdk_amqp_open-1.1.4.dist-info/RECORD
